zootopia3/__init__.py
zootopia3/models/__init__.py
zootopia3/models/cnn.py
zootopia3/models/mlp.py
zootopia3/models/rnn.py
zootopia3/shapes/__init__.py
zootopia3/shapes/circle.py
zootopia3/shapes/diamond.py
zootopia3/shapes/rectangle.py
zootopia3/shapes/shape.py
zootopia3/shapes/triangle.py
zootopia3/simulate/__init__.py
zootopia3/simulate/simulate.py
zootopia3/waves/__init__.py
zootopia3/waves/sine.py
zootopia3-1.2.dist-info/licenses/LICENSE
zootopia3-1.2.dist-info/METADATA
zootopia3-1.2.dist-info/WHEEL
zootopia3-1.2.dist-info/top_level.txt
zootopia3-1.2.dist-info/RECORD
