Metadata-Version: 2.4
Name: zootopia3
Version: 1.2
Summary: Fitting simple torch models
Author-email: "Seth D. Temple" <sethtem@umich.edu>
Project-URL: Homepage, https://github.com/sdtemple/zootopia3
Project-URL: Bug Tracker, https://github.com/sdtemple/zootopia3/issues
Classifier: Programming Language :: Python :: 3
Classifier: License :: OSI Approved :: MIT License
Classifier: Operating System :: OS Independent
Requires-Python: >=3.9
License-File: LICENSE
Requires-Dist: numpy>=2.0
Requires-Dist: scipy>=1.15
Requires-Dist: pandas>=2.0
Requires-Dist: scikit-learn>=1.6
Requires-Dist: xgboost>=3.1.2
Requires-Dist: statsmodels
Requires-Dist: matplotlib>=3.10
Requires-Dist: torch>=2.5
Requires-Dist: transformers>=4.57.0
Requires-Dist: torchvision
Requires-Dist: timm
Requires-Dist: pytest>=7.0.0
Provides-Extra: vizualization
Requires-Dist: seaborn; extra == "vizualization"
Requires-Dist: plotly; extra == "vizualization"
Provides-Extra: notebook
Requires-Dist: jupyterlab>=4.0.0; extra == "notebook"
Requires-Dist: ipykernel>=7.0.1; extra == "notebook"
Dynamic: license-file
